ExtractKit/__init__.py
ExtractKit/bikeExtractor.py
ExtractKit/carExtractor.py
ExtractKit/flipkartExtractor.py
ExtractKit/gadgetsExtractor.py
ExtractKit/newsExtractor.py
ExtractKit/pcBuildExtractor.py
extractkit-1.0.1.dist-info/LICENSE
extractkit-1.0.1.dist-info/METADATA
extractkit-1.0.1.dist-info/WHEEL
extractkit-1.0.1.dist-info/top_level.txt
extractkit-1.0.1.dist-info/RECORD
