Metadata-Version: 2.1
Name: extractkit
Version: 1.0.1
Summary: A Easy Scrapper for scrapping essential data from web (Like Price of car, bike, mobiles, and flipkart, and PC Building components)
Home-page: https://github.com/coders-square/ExtractKit
Author: Karthik Raja, Vignesh R
Author-email: teampcbuild01@gmail.com
License: UNKNOWN
Project-URL: Bug Tracker, https://github.com/coders-square/ExtractKit/issues
Platform: UNKNOWN
Classifier: Programming Language :: Python :: 3
Classifier: License :: OSI Approved :: MIT License
Classifier: Operating System :: OS Independent
Requires-Python: >=3.5
License-File: LICENSE
Requires-Dist: beautifulsoup4
Requires-Dist: requests
